akeneo_api_client/__init__.py
akeneo_api_client/akeneo_client.py
akeneo_api_client/client_builder.py
akeneo_api_client/api/__init__.py
akeneo_api_client/api/asset_api.py
akeneo_api_client/api/asset_attribute_api.py
akeneo_api_client/api/asset_attribute_option_api.py
akeneo_api_client/api/asset_family_api.py
akeneo_api_client/api/attribute_api.py
akeneo_api_client/api/attribute_group_api.py
akeneo_api_client/api/attribute_option_api.py
akeneo_api_client/api/authentication_api.py
akeneo_api_client/api/category_api.py
akeneo_api_client/api/channel_api.py
akeneo_api_client/api/currency_api.py
akeneo_api_client/api/family_api.py
akeneo_api_client/api/family_variant_api.py
akeneo_api_client/api/locale_api.py
akeneo_api_client/api/measure_family_api.py
akeneo_api_client/api/measurement_family_api.py
akeneo_api_client/api/product_model_api.py
akeneo_api_client/api/product_uuid_api.py
akeneo_api_client/api/reference_entity_api.py
akeneo_api_client/api/reference_entity_attribute_api.py
akeneo_api_client/api/reference_entity_attribute_option_api.py
akeneo_api_client/api/reference_entity_record_api.py
akeneo_api_client/api/request/__init__.py
akeneo_api_client/api/request/dict_serialize.py
akeneo_api_client/api/request/json_serializable.py
akeneo_api_client/api/request/line_serialize.py
akeneo_api_client/api/request/list_serialize.py
akeneo_api_client/client/__init__.py
akeneo_api_client/client/akeneo_api_error.py
akeneo_api_client/client/authenticated_http_client.py
akeneo_api_client/client/http_client.py
akeneo_api_client/client/resource_client.py
akeneo_api_client/client/uri_generator.py
akeneo_api_client/pagination/__init__.py
akeneo_api_client/pagination/page.py
akeneo_api_client/pagination/page_factory.py
akeneo_api_client/pagination/resource_cursor.py
akeneo_api_client/search/__init__.py
akeneo_api_client/search/search_builder.py
akeneo_api_client/security/__init__.py
akeneo_api_client/security/authentication.py
akeneo_api_client-1.2.1.dist-info/METADATA
akeneo_api_client-1.2.1.dist-info/WHEEL
akeneo_api_client-1.2.1.dist-info/licenses/LICENSE
akeneo_api_client-1.2.1.dist-info/RECORD
