Metadata-Version: 2.1
Name: akeneo_api_client
Version: 1.2.1
Summary: REST API client for Akeneo
Project-URL: Homepage, https://github.com/asimlqt/akeneo-api-python-client
Project-URL: Bug Tracker, https://github.com/asimlqt/akeneo-api-python-client/issues
Author-email: Asim Liaquat <asm.lqt@gmail.com>
License-File: LICENSE
Classifier: License :: OSI Approved :: MIT License
Classifier: Operating System :: OS Independent
Classifier: Programming Language :: Python :: 3
Requires-Python: >=3.9
Requires-Dist: requests
